bayesflux/__init__.py
bayesflux/_hippylib_utils.py
bayesflux/encoding.py
bayesflux/generation.py
bayesflux/subspace_detection.py
bayesflux-0.7.4.dist-info/WHEEL
bayesflux-0.7.4.dist-info/METADATA
bayesflux-0.7.4.dist-info/RECORD
