Metadata-Version: 2.3
Name: bayesflux
Version: 0.7.4
Summary: Bayesian Fast Linear algebra sUbspace eXtraction in JAX
Author: Joshua Chen, Michael Brennan, Thomas O'Leary-Roseberry
Author-email: Joshua Chen <joshuawchen@icloud.com>, Michael Brennan <mcbrenn@mit.edu>, Thomas O'Leary-Roseberry <tom.olearyroseberry@utexas.edu>
License: MIT License
Requires-Dist: jax
Requires-Dist: jaxlib
Requires-Dist: randlax>=0.3.2
Requires-Dist: pytest ; extra == 'dev'
Requires-Dist: black ; extra == 'dev'
Requires-Dist: isort ; extra == 'dev'
Requires-Dist: flake8 ; extra == 'dev'
Requires-Dist: flake8-pyproject ; extra == 'dev'
Requires-Dist: hickle ; extra == 'hippylib'
Requires-Dist: hippylib>=3.1.0 ; extra == 'hippylib'
Requires-Python: >=3.9
Project-URL: Homepage, https://github.com/joshuawchen/BayesFlux
Project-URL: Repository, https://github.com/joshuawchen/BayesFlux
Provides-Extra: dev
Provides-Extra: hippylib
